Workbook

Sheet 13 Week Cashflow
E1: FEB | I1: MAR | M1: APR | Q1: MAY | V1: JUN | Z1: JUL | AD1: AUG | AH1: SEP | AL1: OCT | AP1: NOV | AT1: DEC | AX1: JAN | BB1: FEB | BF1: MAR
B2: =SUM(E2:AW2)+10000 -> 190279.99 | E2: =SUM(E5:H5) -> 8225 | I2: =SUM(I5:L5) -> 6827 | M2: =SUM(M5:P5) -> 6544.3333 | Q2: =SUM(Q5:U5) -> 9200.5266 | V2: =SUM(V5:Y5) -> 8776.115 | Z2: =SUM(Z5:AC5) -> 10266.813 | AD2: =SUM(AD5:AG5) -> 14127.091 | AH2: =SUM(AH5:AK5) -> 18517.735 | AL2: =SUM(AL5:AO5) -> 24272.973 | AP2: =SUM(AP5:AS5) -> 31816.916 | AT2: =SUM(AT5:AW5) -> 41705.487 | AX2: =SUM(AX5:BA5) -> 54667.386 | BB2: =SUM(BB5:BE5) -> 71657.791 | BF2: =SUM(BF5:BI5) -> 93928.747
B3: Week | D3: 1 | E3: =D3+1 -> 2 | F3: =E3+1 -> 3 | G3: =F3+1 -> 4 | H3: =G3+1 -> 5 | I3: =H3+1 -> 6 | J3: =I3+1 -> 7 | K3: =J3+1 -> 8 | L3: =K3+1 -> 9 | ... BI3: =BH3+1 -> 58
B4: Revenue Run Rate As Of | C4: 46048 | D4: =C4+7 -> 46055 | E4: =D4+7 -> 46062 | F4: =E4+7 -> 46069 | G4: =F4+7 -> 46076 | H4: =G4+7 -> 46083 | I4: =H4+7 -> 46090 | J4: =I4+7 -> 46097 | K4: =J4+7 -> 46104 | ... BI4: =BH4+7 -> 46454
A5: H1 Growth | B5: Shopify Store | C5: =C7/0.33 -> 2545.4545 | D5: 3219 | E5: 2412 | F5: 1905 | G5: 2206 | H5: 1702 | I5: 1748 | J5: 1666 | K5: 1499 | L5: 1914 | M5: 1425 | N5: 1893 | O5: 1593 | P5: =P7/$A$8 -> 1633.3333 | Q5: =Q7/$A$8 -> 1698.6667 | R5: =R7/$A$8 -> 1766.6133 | S5: =S7/$A$8 -> 1837.2779 | T5: =T7/$A$8 -> 1910.769 | U5: =U7/$A$8 -> 1987.1997 | V5: =V7/$A$8 -> 2066.6877 | W5: =W7/$A$8 -> 2149.3552 | ... BI5: =BI7/$A$8 -> 25916.268
A6: 1.04 | B6: Daily Spend | C6: 120 | D6: 120 | E6: 120 | F6: 120 | G6: 60 | H6: =66*1.2 -> 79.2 | I6: 79 | J6: 66 | K6: =J6*$A$6 -> 68.64 | L6: =K6*$A$6 -> 71.3856 | M6: =L6*$A$6 -> 74.241024 | N6: =M6*$A$6 -> 77.210665 | O6: =N6*$A$6 -> 80.299092 | P6: 77 | Q6: =P6*$A$6 -> 80.08 | R6: =Q6*$A$6 -> 83.2832 | S6: =R6*$A$6 -> 86.614528 | T6: =S6*$A$6 -> 90.079109 | U6: =T6*$A$6 -> 93.682273 | V6: =U6*$A$6 -> 97.429564 | W6: =V6*$A$6 -> 101.32675 | X6: =W6*$A$6 -> 105.37982 | ... AC6: =AB6*$A$6 -> 128.21066 | AD6: 150 | AE6: =AD6*$A$11 -> 160.5 | AF6: =AE6*$A$11 -> 171.735 | AG6: =AF6*$A$11 -> 183.75645 | AH6: =AG6*$A$11 -> 196.6194 | AI6: =AH6*$A$11 -> 210.38276 | AJ6: =AI6*$A$11 -> 225.10955 | AK6: =AJ6*$A$11 -> 240.86722 | AL6: =AK6*$A$11 -> 257.72793 | ... BI6: =BH6*$A$11 -> 1221.7669
A7: MER | B7: FB Ad Spend | C7: =C6*7 -> 840 | D7: 820 | E7: =E6*7 -> 840 | F7: =F6*7 -> 840 | G7: =G6*7 -> 420 | H7: 659 | I7: 575 | J7: 460 | K7: =K6*7 -> 480.48 | L7: 514 | M7: 532 | N7: 550 | O7: 580 | P7: =P6*7 -> 539 | Q7: =Q6*7 -> 560.56 | R7: =R6*7 -> 582.9824 | S7: =S6*7 -> 606.3017 | T7: =T6*7 -> 630.55376 | U7: =U6*7 -> 655.77591 | V7: =V6*7 -> 682.00695 | W7: =W6*7 -> 709.28723 | ... BI7: =BI6*7 -> 8552.3685
A8: 0.33 | B8: COGS % | C8: 0.27 | D8: 0.27 | E8: 0.27 | F8: 0.27 | G8: 0.27 | H8: 0.27 | I8: 0.27 | J8: 0.27 | K8: 0.27 | L8: 0.2825 | M8: 0.27 | N8: 0.27 | O8: 0.27 | P8: 0.27 | Q8: 0.27 | R8: 0.27 | S8: 0.27 | T8: 0.27 | U8: 0.27 | V8: 0.27 | W8: 0.27 | X8: 0.27 | Y8: 0.27 | Z8: 0.27 | AA8: 0.27 | AB8: 0.27 | AC8: 0.27 | AD8: 0.27 | AE8: 0.27 | AF8: 0.27 | AG8: 0.27 | AH8: 0.27 | AI8: 0.27 | AJ8: 0.27 | AK8: 0.27 | AL8: 0.27 | AM8: 0.27 | AN8: 0.27 | AO8: 0.27 | AP8: 0.27 | AQ8: 0.27 | AR8: 0.27 | AS8: 0.27 | AT8: 0.27 | AU8: 0.27 | AV8: 0.27 | AW8: 0.27 | AX8: 0.27 | AY8: 0.27 | AZ8: 0.27 | BA8: 0.27 | BB8: 0.27 | BC8: 0.27 | BD8: 0.27 | BE8: 0.27 | BF8: 0.27 | BG8: 0.27 | BH8: 0.27 | BI8: 0.27
B9: Balance Sheet As Of | C9: =C4 -> 46048 | D9: =D4 -> 46055 | E9: =E4 -> 46062 | F9: =F4 -> 46069 | G9: =G4 -> 46076 | H9: =H4 -> 46083 | I9: =I4 -> 46090 | J9: =J4 -> 46097 | ... BI9: =BI4 -> 46454
A10: Weekly Growth | Q10: TARIFF
A11: 1.07 | B11: Shopify Payouts | C11: 120 | D11: 150 | E11: 240 | F11: 43 | G11: 286.26 | H11: 198 | I11: =200 -> 200 | J11: =500+900 -> 1400 | K11: 250 | L11: 262 | M11: =1000-100 -> 900 | N11: =448-148 -> 300 | O11: =150+634+1371 -> 2155 | P11: =109+533 -> 642 | Q11: 906
A12: Profit % | B12: SB - Main (9773) | C12: =2821-200+101 -> 2722 | D12: 4925 | E12: =5714-2441 -> 3273 | F12: 1997.4 | G12: 1805 | H12: =6667-H23 -> 2370 | I12: =7872 -> 7872 | J12: 7963 | K12: 10565 | L12: =11735-25.58 -> 11709.42 | M12: 12273 | N12: 9977 | O12: 9062 | P12: 9728 | Q12: =P21+P65-P43 -> 11588.28 | R12: =Q21+Q65-Q43 -> 7352.0267 | S12: =R21+R65-R43 -> 8821.9587 | T12: =S21+S65-S43 -> 10475.509 | U12: =T21+T65-T43 -> 11960.051 | V12: =U21+U65-U43 -> 10997.413 | W12: =V21+V65-V43 -> 10753.159 | X12: =W21+W65-W43 -> 12567.559 | ... BI12: =BH21+BH65-BH43 -> 208253.82
A13: 0.09 | B13: SB - Sales Tax (6735) | C13: -101.21 | D13: -150 | E13: -244 | F13: -274 | G13: -298 | H13: -306 | I13: -358 | J13: -375 | K13: -422 | L13: -437 | M13: -476 | N13: -523
B14: SB - Corporate Tax (6735) | F14: 0 | G14: 0 | H14: -37 | I14: -37 | J14: -37 | K14: -37 | L14: -37 | M14: -37 | N14: -37
B15: Shopify Capital Repayment | E15: -15 | F15: =-26.28-9.3-20.4 -> -55.98 | G15: -9.3 | H15: -76 | I15: -77.5 | J15: -25 | K15: =-9-18-20-5 -> -52 | L15: -6.3 | M15: -33 | N15: -34 | O15: =-10-34-17 -> -61 | P15: -54
B17: Inventory Cash on Hand | L17: =L23 -> 6210.73
B18: PO | L18: =#REF!*0.3 -> #REF!
B19: Leftover | L19: =L17-L18 -> #REF!
L20: AUG PO 30%
B21: Total Cash On Hand | C21: =SUM(C10:C15) -> 2740.79 | D21: =SUM(D12:D15) -> 4775 | E21: =SUM(E12:E20) -> 3014 | F21: =SUM(F10:F15) -> 1710.42 | G21: =SUM(G10:G15) -> 1783.96 | H21: =SUM(H10:H15) -> 2149 | I21: =SUM(I10:I15) -> 7599.5 | J21: =SUM(J10:J15) -> 8926 | K21: =SUM(K10:K15) -> 10304 | L21: =SUM(L10:L15) -> 11491.12 | M21: =SUM(M10:M15) -> 12627 | ... BI21: =SUM(BI10:BI15) -> 208253.82
B22: Inventory | C22: 17810 | D22: =C22-(D5*D8) -> 16940.87 | E22: 16219 | F22: 15752 | G22: 15386 | H22: =I22-H43 -> 14648 | I22: 14110 | J22: 13632 | K22: 13079 | L22: 12726 | M22: 13199 | N22: 12798 | O22: 12153 | P22: 14601 | Q22: =P22+P43 -> 14160 | R22: =Q22+Q43 -> 13701.36 | S22: =R22+R43 -> 13224.374 | T22: =S22+S43 -> 12728.309 | U22: =T22+T43 -> 12212.402 | V22: =U22+U43 -> 11675.858 | W22: =V22+V43 -> 11117.852 | X22: =W22+W43 -> 10537.526 | ... BI22: =BH22+BH43 -> -81155.755
B23: Working Capital (2465) | E23: 2441 | F23: 2909 | G23: =F23-F43 -> 3589 | H23: 4297 | I23: =H23-H43 -> 4835 | J23: 5363 | K23: 5806 | L23: =K23-K43 -> 6210.73 | M23: =L23-L43-865 -> 5886.435 | N23: =M23-M43 -> 6260.435 | O23: =N23-N43+203 -> 6974.545 | P23: =O23-O43+203-1908 -> 5699.655 | Q23: =P23-P43 -> 6140.655 | R23: =Q23-Q43 -> 6599.295 | S23: =R23-R43 -> 7076.2806 | T23: =S23-S43 -> 7572.3456 | U23: =T23-T43 -> 8088.2532 | V23: =U23-U43 -> 8624.7972 | W23: =V23-V43 -> 9182.8029 | X23: =W23-W43 -> 9763.1288 | ... AD23: =AC23-AC43 -> 13766.388 | AE23: =AD23-AD43+(AD5*$A$13) -> 14911.842 | AF23: =AE23-AE43+(AE5*$A$13) -> 16137.479 | AG23: =AF23-AF43+(AF5*$A$13) -> 17448.91 | AH23: =AG23-AG43+(AG5*$A$13) -> 18852.141 | AI23: =AH23-AH43+(AH5*$A$13) -> 20353.598 | AJ23: =AI23-AI43+(AI5*$A$13) -> 21960.157 | AK23: =AJ23-AJ43+(AJ5*$A$13) -> 23679.176 | AL23: =AK23-AK43+(AK5*$A$13) -> 25518.525 | ... BI23: =BH23-BH43+(BH5*$A$13) -> 130686.42
B24: Total Assets | C24: =SUM(C21:C22) -> 20550.79 | D24: =SUM(D21:D22) -> 21715.87 | E24: =SUM(E21:E22) -> 19233 | F24: =SUM(F21:F22) -> 17462.42 | G24: =SUM(G21:G22) -> 17169.96 | H24: =SUM(H21:H23) -> 21094 | I24: =SUM(I21:I22) -> 21709.5 | J24: =SUM(J21:J22) -> 22558 | K24: =SUM(K21:K22) -> 23383 | L24: =SUM(L21:L22) -> 24217.12 | M24: =SUM(M21:M22) -> 25826 | N24: =SUM(N21:N22) -> 22481 | O24: =SUM(O21:O22) -> 23309 | P24: =SUM(P21:P22) -> 24917 | ... AT24: =SUM(AT21:AT22) -> 34168.424 | AU24: =SUM(AU21:AU23) -> 88518.626 | AV24: =SUM(AV21:AV23) -> 98293.894 | AW24: =SUM(AW21:AW23) -> 108765.68 | AX24: =SUM(AX21:AX22) -> 46395.441 | AY24: =SUM(AY21:AY23) -> 118649.81 | AZ24: =SUM(AZ21:AZ23) -> 131517.58 | BA24: =SUM(BA21:BA23) -> 145298.35 | BB24: =SUM(BB21:BB22) -> 62790.859 | BC24: =SUM(BC21:BC23) -> 158818.94 | BD24: =SUM(BD21:BD23) -> 175740.35 | BE24: =SUM(BE21:BE23) -> 193858.51 | BF24: =SUM(BF21:BF22) -> 84955.201 | BG24: =SUM(BG21:BG23) -> 211745.97 | BH24: =SUM(BH21:BH23) -> 233980.88 | BI24: =SUM(BI21:BI23) -> 257784.48
B26: ST Liabilities
B27: Ads Payable (01000) | C27: 327 | D27: =324 -> 324 | E27: =166+1076 -> 1242 | F27: =-330-227 -> -557 | G27: =758+115-75 -> 798 | H27: =160.73+54+54+327 -> 595.73 | I27: =1110+148 -> 1258 | J27: =1683+70 -> 1753 | K27: =2013+193+268 -> 2474 | L27: =2893+330 -> 3223 | M27: =3422+200 -> 3622 | N27: =3802-1000-83 -> 2719 | O27: =3971+297-1000 -> 3268 | P27: =4671+172-1000 -> 3843 | Q27: =P27+P7-P47 -> 4382 | R27: =Q27+Q7-Q47 -> 560.56 | S27: =R27+R7-R47 -> 1143.5424 | T27: =S27+S7-S47 -> 1749.8441 | U27: =T27+T7-T47 -> 2380.3979 | V27: =U27+U7-U47 -> 655.77591 | W27: =V27+V7-V47 -> 1337.7829 | X27: =W27+W7-W47 -> 2047.0701 | ... BI27: =BH27+BH7-BH47 -> 28968.679
B28: Fullfillment Payable (2907) | C28: =1333*0.75 -> 999.75 | D28: =1333 -> 1333 | E28: =D28-D62+(E$5*$A$46)+(OPEX!$I$28/4) -> 1723.7 | F28: =448+(2*(OPEX!$I$28/4)) -> 747 | G28: =F28-F62+(G$5*$A$46)+(OPEX!$I$28/4) -> 1117.1 | H28: =(1424*1.03) -> 1466.72 | I28: =(H28-H62)+(H$5*$A$46)+(OPEX!$I$28/4) -> 1786.42 | J28: =(I28-I62)+(I$5*$A$46)+(OPEX!$I$28/4) -> 644.72 | K28: =(J28-J62)+(J$5*$A$46)+(OPEX!$I$28/4) -> 960.82 | L28: 1499 | M28: =(L28-L62)+(L$5*$A$46)+(OPEX!$I$28/4) -> 1839.9 | N28: =(M28-M62)+(M$5*$A$46)+(OPEX!$I$28/4) -> 632.9 | O28: =(N28-N62)+(N$5*$A$46)+(OPEX!$I$28/4) -> 971.7 | P28: =(O28-O62)+(O$5*$A$46)+(OPEX!$I$28/4) -> 1280.5 | Q28: =(P28-P62)+(P$5*$A$46)+(OPEX!$I$28/4) -> 1593.3333 | R28: =(Q28-Q62)+(Q$5*$A$46)+(OPEX!$I$28/4) -> 319.36667 | S28: =(R28-R62)+(R$5*$A$46)+(OPEX!$I$28/4) -> 645.528 | T28: =(S28-S62)+(S$5*$A$46)+(OPEX!$I$28/4) -> 978.75579 | ... BI28: =(BH28-BH62)+(BH$5*$A$46)+(OPEX!$I$28/4) -> 29626.506
B29: Paid In Capital
B30: LT Liabilities
A31: OPEX CARDS | B31: CHASE 5718 | H31: 648 | I31: 648 | J31: =I31-I50 -> 648 | K31: 658 | L31: =K31-K50 -> 658 | M31: =L31-L50 -> 658 | X31: =W32*1.05 -> 1890 | Y31: =X31-X50 -> 1890 | Z31: =Y31-Y50 -> 1890 | AA31: =Z31-Z50 -> 1710 | AB31: =AA31-AA50 -> 1710 | AC31: =AB31-AB50 -> 1710 | AD31: =AC31-AC50 -> 1710 | AE31: =AD31-AD50 -> 1530 | AF31: =AE31-AE50 -> 1530 | ... BI31: =BH31-BH50 -> 270
B32: AMEX PLUM 0000 | C32: 734 | D32: =C32-D51 -> 734 | E32: =D32-E51 -> 734 | F32: =E32-F51 -> 734 | G32: =F32-G51 -> 734 | H32: 959.32 | I32: =H32-H51 -> 959.32 | J32: 812.46 | K32: =J32-J51 -> 812.46 | L32: =K32-K51 -> 812.46 | M32: =812+2162 -> 2974 | N32: =M32-M51 -> 2364 | O32: =N32-N51 -> 2364 | P32: =O32-O51 -> 2364 | Q32: =P32-P51 -> 2364 | R32: =Q32-Q51 -> 1946 | S32: =R32-R51 -> 1946 | T32: =S32-S51 -> 1946 | U32: =T32-T51 -> 1946 | ... W32: =V32-V51 -> 1800 | X32: 0 | Y32: =X32-X51 -> 0 | Z32: =Y32-Y51 -> 0 | AA32: =Z32-Z51 -> 0 | AB32: =AA32-AA51 -> 0 | AC32: =AB32-AB51 -> 0 | AD32: =AC32-AC51 -> 0 | AE32: =AD32-AD51 -> 0 | AF32: =AE32-AE51 -> 0 | ... BI32: =BH32-BH51 -> 0
B33: AMEX BLUE 71005 | C33: 17173 | D33: =C33-D52 -> 17000 | E33: =D33-E52 -> 17000 | F33: =E33-F52 -> 17000 | G33: =F33-G52 -> 17000 | H33: 16831 | I33: =H33-I52 -> 16831 | J33: =I33-J52 -> 16831 | K33: =J33-K52 -> 16831 | L33: =K33-L52 -> 16658 | M33: 16809 | N33: =M33-N52 -> 16809 | O33: =N33-O52 -> 16809 | P33: =O33-P52 -> 16809 | Q33: =P33-Q52 -> 16642 | R33: =Q33-R52 -> 16642 | S33: =R33-S52 -> 16642 | T33: =S33-T52 -> 16642 | U33: =T33-U52 -> 16469 | ... BI33: =BH33-BI52 -> 11048
B34: Shopify Capital | C34: 18080 | D34: =C34-D53 -> 17886.86 | E34: =D34-E53 -> 17742.14 | F34: 17623 | G34: =17563-9.3 -> 17553.7 | H34: 17440 | I34: 17354 | J34: 17284 | K34: =J34-J53 -> 17184.04 | L34: =K34-K53 -> 17094.1 | M34: 16984 | N34: 16901 | O34: =N34-N53 -> 16787.42 | P34: 16651 | Q34: =P34-P53 -> 16553 | R34: =Q34-Q53 -> 16451.08 | S34: =R34-R53 -> 16345.083 | T34: =S34-S53 -> 16234.847 | U34: =T34-T53 -> 16120.2 | V34: =U34-U53 -> 16000.968 | W34: =V34-V53 -> 15876.967 | X34: =W34-W53 -> 15748.006 | ... BI34: =BH34-BH53 -> -7339.8001
B35: Long Term Loan | C35: 20000 | D35: =C35-C54 -> 20000 | E35: =D35-D54 -> 20000 | F35: =E35-E54 -> 20000 | G35: =F35-F54 -> 20000 | H35: =G35-G54 -> 20000 | I35: =H35-H54 -> 20000 | J35: =I35-I54 -> 20000 | K35: =J35-J54 -> 20000 | ... BI35: =BH35-BH54 -> 20000
B37: Total Liabilities | C37: =SUM(C27:C36) -> 57313.75 | D37: =SUM(D27:D36) -> 57277.86 | E37: =SUM(E27:E36) -> 58441.84 | F37: =SUM(F27:F36) -> 55547 | G37: =SUM(G27:G36) -> 57202.8 | H37: =SUM(H27:H36) -> 57940.77 | I37: =SUM(I27:I36) -> 58836.74 | J37: =SUM(J27:J36) -> 57973.18 | ... BI37: =SUM(BI27:BI36) -> 82573.385
B38: Total Equity | C38: =C24-C37 -> -36762.96 | D38: =D24-D37 -> -35561.99 | E38: =E24-E37 -> -39208.84 | F38: =F24-F37 -> -38084.58 | G38: =G24-G37 -> -40032.84 | H38: =H24-H37 -> -36846.77 | I38: =I24-I37 -> -37127.24 | J38: =J24-J37 -> -35415.18 | ... BI38: =BI24-BI37 -> 175211.1
B39: Net Cash of ST Liabilities | C39: =C21-C27-C28 -> 1414.04 | D39: =D21-D27-D28 -> 3118 | E39: =E21-E27-E28 -> 48.3 | F39: =F21-F27-F28 -> 1520.42 | G39: =G21-G27-G28 -> -131.14 | H39: =H21-H27-H28 -> 86.55 | I39: =I21-I27-I28-I23 -> -279.92 | J39: =J21-J27-J28-J23 -> 1165.28 | K39: =K21-K27-K28-K23 -> 1063.18 | L39: =L21-L27-L28-L23 -> 558.39 | M39: =M21-M27-M28-M23 -> 1278.665 | N39: =N21-N27-N28-N23 -> 70.665 | O39: =O21-O27-O28-O23 -> -58.245 | P39: =P21-P27-P28-P23 -> -507.155 | ... BI39: =BI21-BI27-BI28-BI23 -> 18972.216
B40: Projected Statement of Cashflows For WK Starting | C40: =C9 -> 46048 | D40: =D9 -> 46055 | E40: =E9 -> 46062 | F40: =F9 -> 46069 | G40: =G9 -> 46076 | H40: =H9 -> 46083 | I40: =I9 -> 46090 | J40: =J9 -> 46097 | ... BI40: =BI9 -> 46454
A41: PP % | B41: Inflows
A42: 0.04 | B42: Online Store | C42: =C5*0.965 -> 2456.3636 | D42: =D5*0.965 -> 3106.335 | E42: =(E5*(1-$A$42)) -> 2315.52 | F42: 1273 | G42: =(G5*(1-$A$42)) -> 2117.76 | H42: =(H5*(1-$A$42)) -> 1633.92 | I42: =(I5*(1-$A$42)) -> 1678.08 | J42: =(J5*(1-$A$42)) -> 1599.36 | K42: =(K5*(1-$A$42)) -> 1439.04 | L42: =(L5*(1-$A$42)) -> 1837.44 | M42: =(M5*(1-$A$42)) -> 1368 | N42: =(N5*(1-$A$42)) -> 1817.28 | ... BI42: =(BI5*(1-$A$42)) -> 24879.618
B43: Transfer to WC (6848) | E43: =-(E5*E8) -> -651.24 | F43: -680 | G43: =-(G5*G8) -> -595.62 | H43: -538 | I43: =-(I5*I8) -> -471.96 | J43: =-(J5*J8) -> -449.82 | K43: =-(K5*K8) -> -404.73 | L43: =-(L5*L8) -> -540.705 | M43: -374 | N43: =-(N5*N8) -> -511.11 | O43: =-(O5*O8) -> -430.11 | P43: =-(P5*P8) -> -441 | Q43: =-(Q5*Q8) -> -458.64 | R43: =-(R5*R8) -> -476.9856 | S43: =-(S5*S8) -> -496.06502 | T43: =-(T5*T8) -> -515.90762 | U43: =-(U5*U8) -> -536.54393 | ... BI43: =-(BI5*BI8) -> -6997.3924
B44: Total Inflows | C44: =SUM(C42:C43) -> 2456.3636 | D44: =SUM(D42:D43) -> 3106.335 | E44: =SUM(E42:E43) -> 1664.28 | F44: =SUM(F42:F43) -> 593 | G44: =SUM(G42:G43) -> 1522.14 | H44: =SUM(H42:H43) -> 1095.92 | I44: =SUM(I42:I43) -> 1206.12 | J44: =SUM(J42:J43) -> 1149.54 | ... BI44: =SUM(BI42:BI43) -> 17882.225
A45: Fulfillment %
A46: 0.1 | B46: Outflows
A47: Variable Overhead | B47: Ads Payable (01000) | C47: =C7 -> 840 | D47: 324 | E47: =E27 -> 1242 | F47: =F7 -> 840 | G47: =G7 -> 420 | H47: =H7 -> 659 | M47: 356 | Q47: =Q27 -> 4382 | U47: =U27 -> 2380.3979 | Y47: =Y27 -> 2784.7288 | AC47: =AC27 -> 3257.7388 | AG47: =AG27 -> 4273.1196 | AK47: =AK27 -> 5711.0771 | AO47: =AO27 -> 7486.0571 | AS47: =AS27 -> 9812.6938 | AW47: =AW27 -> 12862.44 | BA47: =BA27 -> 16860.035 | BE47: =BE27 -> 22100.067 | BI47: =BI27 -> 28968.679
B48: Fullfillment Payable (2907)
G49: "225
A50: Working Capital | B50: CHASE 5718 | M50: 658 | Z50: 180 | AD50: 180 | AH50: 180 | AL50: 180 | AP50: 180 | AT50: 180 | AX50: 180 | BB50: 180 | BF50: 180
B51: AMEX PLUM 0000 | I51: =74+74 -> 148 | M51: 610 | Q51: 418 | V51: 146
B52: AMEX BLUE 71005 | D52: 173 | H52: 173 | L52: 173 | Q52: 167 | U52: 173 | Y52: 173 | AC52: 173 | AG52: 175 | AH52: 175 | AI52: 175 | AJ52: 175 | AK52: 175 | AL52: 175 | AM52: 175 | AN52: 175 | AO52: 175 | AP52: 175 | AQ52: 175 | AR52: 175 | AS52: 175 | AT52: 175 | AU52: 175 | AV52: 175 | AW52: 175 | AX52: 175 | AY52: 175 | AZ52: 175 | BA52: 175 | BB52: 175 | BC52: 175 | BD52: 175 | BE52: 175 | BF52: 175 | BG52: 175 | BH52: 175 | BI52: 175
B53: Shopify Capital | C53: =C5*0.06 -> 152.72727 | D53: =D5*0.06 -> 193.14 | E53: =E5*0.06 -> 144.72 | F53: =F5*0.06 -> 114.3 | G53: =G5*0.06 -> 132.36 | H53: =H5*0.06 -> 102.12 | I53: =I5*0.06 -> 104.88 | J53: =J5*0.06 -> 99.96 | ... X53: =X5*0.06 -> 134.11977 | Y53: =X34-12897 -> 2851.0058 | Z53: =Z5*0.06 -> 145.06394 | AA53: =AA5*0.06 -> 150.8665 | AB53: =AB5*0.06 -> 156.90116 | AC53: =AC5*0.06 -> 163.1772 | AD53: =AD5*0.06 -> 190.90909 | AE53: =AE5*0.06 -> 204.27273 | AF53: =AF5*0.06 -> 218.57182 | AG53: =AG5*0.06 -> 233.87185 | ... BI53: =BI5*0.06 -> 1554.9761
B54: LT Loan (Nathan)
A55: % of Ad Spend
A56: 0
A57: Fixed Overhead | B57: Creative Production | E57: 0 | F57: =F7*$A$56 -> 0 | G57: 0 | H57: =H7*$A$56 -> 0 | I57: =I7*$A$56 -> 0 | J57: =J7*$A$56 -> 0 | K57: =K7*$A$56 -> 0 | L57: =L7*$A$56 -> 0 | M57: =M7*$A$56 -> 0 | N57: =N7*$A$56 -> 0 | O57: =O7*$A$56 -> 0 | ... BI57: =BI7*$A$56 -> 0
B58: Salary
B59: G&A | D59: =372.92+60+173 -> 605.92 | H59: =80+60 -> 140 | K59: =OPEX!$O8 -> 235.15 | L59: =OPEX!$O5 -> 197.72 | M59: =OPEX!$O6 -> 110.72 | N59: =OPEX!$O7 -> 120.02 | O59: =OPEX!$O8 -> 235.15 | P59: =OPEX!$O5 -> 197.72 | Q59: =OPEX!$O6 -> 110.72 | R59: =OPEX!$O7 -> 120.02 | T59: =OPEX!$O8 -> 235.15 | U59: =OPEX!$O5 -> 197.72 | V59: =OPEX!$O6 -> 110.72 | W59: =OPEX!$O7 -> 120.02 | X59: =OPEX!$O8 -> 235.15 | Y59: =OPEX!$O5 -> 197.72 | Z59: =OPEX!$O6 -> 110.72 | AA59: =OPEX!$O7 -> 120.02 | AB59: =OPEX!$O8 -> 235.15 | AC59: =OPEX!$O5 -> 197.72 | AD59: =OPEX!$O6 -> 110.72 | AE59: =OPEX!$O7 -> 120.02 | AH59: =OPEX!I5 -> 478.08 | AL59: =OPEX!I5 -> 478.08 | AN59: =OPEX!Q5 -> 0 | AQ59: =OPEX!I5 -> 478.08 | AV59: =OPEX!S5 -> 0 | AZ59: =OPEX!W5 -> 0 | BD59: =OPEX!AA5 -> 0 | BH59: =OPEX!AE5 -> 0
B60: R&D | V60: 180 | Z60: 180 | AD60: 180 | AH60: 180 | AL60: 180 | AP60: 180 | AT60: 180 | AX60: 180
B61: Interest | D61: =OPEX!I32 -> 125 | H61: 250 | M61: 250 | Q61: 0 | U61: 0 | Y61: 0 | AC61: 0 | AH61: =OPEX!I32 -> 125 | AL61: =OPEX!I32 -> 125 | AN61: =OPEX!Q32 -> 0 | AP61: =OPEX!I32 -> 125 | AT61: =OPEX!I32 -> 125 | AV61: =OPEX!S32 -> 0 | AX61: =OPEX!I32 -> 125 | AZ61: =OPEX!W32 -> 0 | BA61: =OPEX!X32 -> 0 | BD61: =OPEX!AA32 -> 0 | BE61: =OPEX!AB32 -> 0 | BH61: =OPEX!AE32 -> 0 | BI61: =OPEX!AF32 -> 0
B62: Fulfillment | E62: 1333 | I62: =1551-85 -> 1466 | M62: 1499 | Q62: =Q28 -> 1593.3333 | S62: =OPEX!Q6 -> 0 | V62: =V28 -> 1667.5527 | Z62: =Y28 -> 1093.6372 | AD62: =AC28 -> 1585.1936 | AI62: =AH28 -> 2432.1711 | AM62: =AL28 -> 2449.7735 | AQ62: =AP28 -> 3025.2973
B64: Total Outflows | C64: =SUM(C47:C63) -> 992.72727 | D64: =SUM(D47:D63) -> 1421.06 | E64: =SUM(E47:E63) -> 2719.72 | F64: =SUM(F47:F63) -> 954.3 | G64: =SUM(G47:G63) -> 552.36 | H64: =SUM(H47:H63) -> 1324.12 | I64: =SUM(I47:I63) -> 1718.88 | J64: =SUM(J47:J63) -> 99.96 | ... BI64: =SUM(BI47:BI63) -> 30698.655
B65: Net Cash Flow | C65: =C44-C64 -> 1463.6364 | D65: =D44-D64 -> 1685.275 | E65: =E44-E64 -> -1055.44 | F65: =F44-F64 -> -361.3 | G65: =G44-G64 -> 969.78 | H65: =H44-H64 -> -228.2 | I65: =I44-I64 -> -512.76 | J65: =J44-J64 -> 1049.58 | ... BI65: =BI44-BI64 -> -12816.43
B66: Week # | D66: 1 | E66: 2 | F66: 3 | G66: 4 | H66: 5 | I66: 6 | J66: 7 | K66: 8 | L66: 9 | M66: 10 | N66: 11 | O66: 12 | P66: 13 | Q66: 14 | R66: 15 | S66: 16 | T66: 17 | U66: 18 | V66: 19 | W66: 20 | X66: 21 | Y66: 22 | Z66: 23 | AA66: 24 | AB66: 25 | AC66: 26 | AD66: 27 | AE66: 28 | AF66: 29 | AG66: 30 | AH66: 27 | AI66: 28 | AJ66: 29 | AK66: 30 | AL66: 27 | AM66: 28 | AN66: 29 | AO66: 30 | AP66: 27 | AQ66: 28 | AR66: 29 | AS66: 30 | AT66: 27 | AU66: 28 | AV66: 29 | AW66: 30 | AX66: 27 | AY66: 28 | AZ66: 29 | BA66: 30 | BB66: 27 | BC66: 28 | BD66: 29 | BE66: 30 | BF66: 27 | BG66: 28 | BH66: 29 | BI66: 30
B68: WORKING CAPITAL | E68: =E23+E22 -> 18660 | F68: =F23+F22 -> 18661 | G68: =G23+G22 -> 18975 | H68: =H23+H22 -> 18945 | I68: =I23+I22 -> 18945 | J68: =J23+J22 -> 18995 | K68: =K23+K22 -> 18885 | L68: =L23+L22 -> 18936.73 | ... BI68: =BI23+BI22 -> 49530.662
B69: Owed | E69: =E68-E35 -> -1340 | F69: =F68-F35 -> -1339 | G69: =G68-G35 -> -1025 | H69: =H68-H35 -> -1055 | I69: =I68-I35 -> -1055 | J69: =J68-J35 -> -1005 | K69: =K68-K35 -> -1115 | L69: =L68-L35 -> -1063.27 | ... BI69: =BI68-BI35 -> 29530.662
B71: Key Performance Indicators For WK Ending | C71: =C46 -> 0 | D71: =D46 -> 0 | E71: =E46 -> 0 | F71: =F46 -> 0 | G71: =G46 -> 0 | H71: 46083 | I71: =H71+7 -> 46090 | J71: =J46 -> 0 | K71: =K46 -> 0 | L71: =L46 -> 0 | M71: =M46 -> 0 | N71: =N46 -> 0 | O71: =O46 -> 0 | P71: =P46 -> 0 | Q71: =Q46 -> 0 | ... BI71: =BI46 -> 0
B72: Contribution Margin | C72: =C40 -> 46048 | D72: =D40 -> 46055 | E72: =E40 -> 46062 | F72: =F40 -> 46069 | G72: =G40 -> 46076 | H72: 662 | I72: 165 | J72: 296 | K72: 348 | L72: 187 | M72: 361 | N72: 225 | O72: 484 | P72: 124
B73: Net Profit | H73: 290 | I73: -175 | J73: -45 | K73: 7 | L73: -154 | M73: 12 | N73: -128 | O73: 132 | P73: -228
B74: NC CPA | H74: 34 | I74: 58 | J74: 72 | K74: 46 | L74: 45 | M74: 40 | N74: 66 | O74: 55 | P74: 41
B75: WoM | H75: 0.33 | I75: 0 | J75: 0 | K75: 0 | L75: 0 | M75: 0 | N75: 0 | O75: 0 | P75: 0
B76: EC Revenue | H76: 0.277 | I76: 0.2857 | J76: 0.35 | K76: 0.1336 | L76: 0.0785 | M76: 0.069 | N76: 0.28 | O76: 0.13 | P76: 0.003
K77: 118

Sheet OPEX
D1: Rev/m | E1: Rev/wk | F1: Rev /d | G1: Spend /d
D2: =E2*4 -> 36405.413 | E2: =F2*7 -> 9101.3533 | F2: =(F3/0.1/30) -> 1300.1933 | G2: =(F2*0.33) -> 429.0638 | J2: Annual G&A
C3: Monthly G&A | F3: =SUM(F5:F65)+L10 -> 3900.58 | J3: Legal
C4: Cost | D4: Monthly | E4: Active Accounts | F4: Total | G4: Date | H4: rev/mo | J4: Cost | K4: Yearly | L4: Date | N4: Cash Flow | O4: Amount | P4: Date
A5: Subscriptions | B5: Mandatory | C5: Slack | D5: 9.3 | E5: 1 | F5: =D5*E5 -> 9.3 | G5: 18th | H5: =F5/0.1 -> 93 | I5: =SUM(F5:F25) -> 478.08 | J5: Franchise Tax | K5: 225 | L5: Mar 1st | N5: 1st Week | O5: =F6+F9+F15+F23+O6 -> 197.72 | P5: 1 to 7
C6: Google | D6: 17 | E6: 1 | F6: =D6*E6 -> 17 | G6: 1st | J6: Filing fees | K6: 330 | L6: Apr 15th | N6: 2nd Week | O6: =F20+F22+F17 -> 110.72 | P6: 8 to 14
C7: Shopify | D7: 42 | E7: 1 | F7: =D7*E7 -> 42 | G7: 29th | J7: Agent fee | K7: 120 | L7: Sept 6th | N7: 3rd Week | O7: =F5+F13+F18+F22+F17 -> 120.02 | P7: 15 to 22
C8: Finaloop | D8: =155*0.85 -> 131.75 | E8: 1 | F8: =D8*E8 -> 131.75 | G8: 28th | J8: Plum Card | K8: 250 | L8: Nov 14th | N8: 4th Week | O8: =F8+F7+F10++F24+F14 -> 235.15 | P8: 23 to 30
C9: Phone | D9: 60 | E9: 1 | F9: =D9*E9 -> 60 | G9: 1st | J9: Chase Biz Preferred | K9: 95 | L9: Mar 8th
C10: Kintsugi | D10: 80 | E10: 0.33 | F10: =D10*E10 -> 26.4 | G10: 30th | K10: =SUM(K5:K9) -> 1020 | L10: =K10/12 -> 85
C11: Notion | D11: 27 | E11: 0.33 | F11: =D11*E11 -> 8.91 | G11: 30th
B13: Revenue / Cost | C13: Klaviyo | D13: 150 | E13: 0 | F13: =D13*E13 -> 0 | G13: 20th | H13: =D13/0.1 -> 1500
C14: Kleio | D14: 29 | E14: 1 | F14: =D14*E14 -> 29 | G14: 29th | H14: =D14/0.1 -> 290
C15: Higgsfield | D15: 150 | E15: 0 | F15: =D15*E15 -> 0 | G15: 2nd | H15: =D15/0.1 -> 1500 | K15: /mo | L15: /yr
C16: Foreplay | D16: 65 | E16: 0 | F16: =D16*E16 -> 0 | H16: =D16/0.1 -> 650 | J16: Mandatory | K16: =SUM(F5:F10) -> 286.45 | L16: =K16*12 -> 3437.4
C17: Claude | D17: 100 | E17: 1 | F17: =D17*E17 -> 100 | G17: 12th | H17: =D17/0.1 -> 1000 | J17: Revenue / Cost | K17: =SUM(F13:F17) -> 129 | L17: =K17*12 -> 1548
C18: Computer | D18: 180 | E18: 0 | F18: =D18*E18 -> 0 | G18: 20th | H18: =D18/0.1 -> 1800 | J18: Luxury | K18: =SUM(F20:F25) -> 53.72 | L18: =K18*12 -> 644.64
B20: Luxury | C20: Adobe | D20: 45.5 | E20: 0 | F20: =D20*E20 -> 0 | G20: 8th
C21: Clo3d | D21: 25 | E21: 1 | F21: =D21*E21 -> 25 | G21: 9th
C22: Microsoft | D22: 10 | E22: 1 | F22: 10.72 | G22: 13th
C23: AquaVoice | D23: 10 | E23: 1 | F23: =D23*E23 -> 10 | G23: 4th
C24: Figma | D24: 6 | E24: 1 | F24: =D24*E24 -> 6 | G24: 28th
C25: NordPass | D25: 2 | E25: 1 | F25: =D25*E25 -> 2 | G25: 13th
A28: Fulfillment | C28: Admin & Tech | D28: 388 | E28: 1 | F28: =D28*E28 -> 388 | G28: 7th | I28: =SUM(F28:F31) -> 598
C29: Bins | D29: 5 | E29: 31 | F29: =D29*E29 -> 155 | G29: 7th
C30: Pallets | D30: 35 | E30: 1 | F30: =D30*E30 -> 35 | G30: 7th
C31: Returns | D31: 4 | E31: 5 | F31: =D31*E31 -> 20 | G31: 7th
C32: Nathan Belete | D32: 125 | E32: 1 | F32: =D32*E32 -> 125 | G32: 1st | I32: =SUM(F32:F33) -> 125
A34: Payroll | C34: Matias Belete - 1 | D34: 729 | E34: 1 | F34: =D34*E34 -> 729 | G34: 16th | I34: =SUM(F34:F35) -> 1458
C35: Matias Belete - 2 | D35: 729 | E35: 1 | F35: =D35*E35 -> 729 | G35: 30th
C36: Scale Software | D36: =D41 -> 1156.5 | E36: 1 | F36: =D36*E36 -> 1156.5 | G36: 30th
D41: =SUM(D42:D89) -> 1156.5
B42: Marketing | C42: Smile Loyalty | D42: 15 | E42: 0 | F42: =D42*E42 -> 0 | G42: 1st
A43: Scaling Software | C43: Mida Heatmap | D43: 20 | E43: 0 | F43: =D43*E43 -> 0 | G43: 1st
C44: Replo LDPs | D44: 99 | E44: 0 | F44: =D44*E44 -> 0 | G44: 1st
C45: Intelligems | D45: 50 | E45: 0 | F45: =D45*E45 -> 0 | G45: 1st
C46: Motion | D46: 250 | E46: 0 | F46: =D46*E46 -> 0 | G46: 1st
C47: Foreplay | D47: 60 | E47: 0 | F47: =D47*E47 -> 0 | G47: 1st
C48: Manus | D48: 100 | E48: 0 | F48: =D48*E48 -> 0 | G48: 1st
C49: Virtue - Charity
B51: Product | C51: Clo3d | D51: =55-25 -> 30 | E51: 0 | F51: =D51*E51 -> 0 | G51: 1st
C52: Pantone Connect | D52: =90/12 -> 7.5 | E52: 0 | F52: =D52*E52 -> 0 | G52: 1st
C53: Particl | D53: 250 | E53: 0 | F53: =D53*E53 -> 0 | G53: 1st
B58: Operations | C58: Shopify Grow | D58: =105-45 -> 60 | E58: 0 | F58: =D58*E58 -> 0 | G58: 1st
C59: Loom | D59: 18 | E59: 0 | F59: =D59*E59 -> 0 | G59: 1st
C60: Rich Panel | D60: 89 | E60: 0 | F60: =D60*E60 -> 0 | G60: 1st
C61: Kiwi Size Chart | D61: 7 | E61: 0 | F61: =D61*E61 -> 0 | G61: 1st
C62: Delivery Date | D62: 8 | E62: 0 | F62: =D62*E62 -> 0 | G62: 1st
C63: Aftersell | D63: 27 | E63: 0 | F63: =D63*E63 -> 0 | G63: 1st
C64: AfterShip Returns | D64: 11 | E64: 0 | F64: =D64*E64 -> 0 | G64: 1st
C65: Gusto | D65: =49+6 -> 55 | E65: 0 | F65: =D65*E65 -> 0 | G65: 1st
